scikitmcda/__init__.py
scikitmcda/constants.py
scikitmcda/dmuu.py
scikitmcda/electre_i.py
scikitmcda/electre_ii.py
scikitmcda/ensemble.py
scikitmcda/mcda.py
scikitmcda/promethee_ii.py
scikitmcda/topsis.py
scikitmcda/vikor.py
scikitmcda/waspas.py
scikitmcda/wpm.py
scikitmcda/wsm.py
scikit_mcda-0.21.47.dist-info/LICENSE
scikit_mcda-0.21.47.dist-info/METADATA
scikit_mcda-0.21.47.dist-info/WHEEL
scikit_mcda-0.21.47.dist-info/top_level.txt
scikit_mcda-0.21.47.dist-info/RECORD
