Metadata-Version: 2.1
Name: scikit-mcda
Version: 0.21.47
Summary: Library for Multi-criteria Decision Aid Methods
Home-page: https://gitlab.com/cybercrafter/scikit-mcda
Author: Antonio Horta
Author-email: ajhorta@cybercrafter.com.br
License: Apache License 2.0
Platform: UNKNOWN
Classifier: Programming Language :: Python
Classifier: License :: OSI Approved :: Apache Software License
Classifier: Operating System :: OS Independent
Classifier: Topic :: Software Development :: Libraries
Classifier: Topic :: Scientific/Engineering :: Mathematics
Requires-Python: >=3.6
Requires-Dist: numpy (~=1.18)
Requires-Dist: pandas (~=1.0)
Requires-Dist: tabulate
